[{"title":"Materias y Registros Procesamiento","id":"ckwg.US.base.6.04"},{"title":"Drama y Baile","id":"ckwg.US.base.3.03"},{"title":"Detalles de Matematicas","id":"ckwg.US.base.6.01"},{"title":"Promoción","id":"ckwg.US.base.5.07"},{"title":"Deportes","id":"ckwg.US.base.4.05"},{"title":"Communicaciones Verbal","id":"ckwg.US.base.6.03"},{"title":"Operacion de Sistemas","id":"ckwg.US.base.1.1"},{"title":"Cuiadado de Niño y Adultos","id":"ckwg.US.base.4.03"},{"title":"Detalles de Administracion","id":"ckwg.US.base.6.05"},{"title":"Practica y Apoyo Legal","id":"ckwg.US.base.5.03"},{"title":"Operacion de Herramientas","id":"ckwg.US.base.1.11"},{"title":"Ingeniería","id":"ckwg.US.base.2.08"},{"title":"Manufactura y Producion","id":"ckwg.US.base.1.12"},{"title":"Agricultuares y Recursos Naturales","id":"ckwg.US.base.1.01"},{"title":"Gobierno y Administración Publica","id":"ckwg.US.base.5.06"},{"title":"Ventas y Compras","id":"ckwg.US.base.5.01"},{"title":"Matematicas y Análisis de Datos","id":"ckwg.US.base.2.06"},{"title":"Preparacion de Comida","id":"ckwg.US.base.1.09"},{"title":"Hospitalidad, Belleza y Servicio de atencion al Clinte","id":"ckwg.US.base.5.02"},{"title":"Communicaciones","id":"ckwg.US.base.3.05"},{"title":"Arte de Literatura","id":"ckwg.US.base.3.01"},{"title":"Ingeniería","id":"ckwg.US.base.1.03"},{"title":"Regulacion de Ejecución","id":"ckwg.US.base.5.08"},{"title":"Detalles de Finanzas","id":"ckwg.US.base.6.02"},{"title":"Ciencias de Salud","id":"ckwg.US.base.2.03"},{"title":"Finanzas","id":"ckwg.US.base.5.05"},{"title":"Ciencias de Computucion y Tecnologia","id":"ckwg.US.base.2.05"},{"title":"Manualidades de Metal, Madera, Plastico y Tela","id":"ckwg.US.base.1.08"},{"title":"Laboratiro y Medico Tecnologia","id":"ckwg.US.base.2.04"},{"title":"Música","id":"ckwg.US.base.3.04"},{"title":"Manualidades Electricos","id":"ckwg.US.base.1.07"},{"title":"Construcion y Apoyo","id":"ckwg.US.base.1.05"},{"title":"Manualidades Mecánicos","id":"ckwg.US.base.1.06"},{"title":"Ciencias Naturales","id":"ckwg.US.base.2.02"},{"title":"Administracion de Empresas","id":"ckwg.US.base.5.04"},{"title":"Transportacion y Distrubacion","id":"ckwg.US.base.1.04"},{"title":"Enfermeria, Terapia y Promoción de Salud","id":"ckwg.US.base.4.02"},{"title":"Ciencias Sociales","id":"ckwg.US.base.2.07"},{"title":"Seguiridad y Refuerzos de la Ley","id":"ckwg.US.base.1.02"},{"title":"Servicios de Libreria Educacional","id":"ckwg.US.base.4.04"},{"title":"Servicios Sociales","id":"ckwg.US.base.4.01"},{"title":"Ciencas Fisico","id":"ckwg.US.base.2.01"},{"title":"Arte Visuales","id":"ckwg.US.base.3.02"}]